ProgrammingPracticeTutorialsKaistCs109/README.md
ProgrammingPracticeTutorialsKaistCs109/__init__.py
ProgrammingPracticeTutorialsKaistCs109/__main__.py
ProgrammingPracticeTutorialsKaistCs109/file.epub
ProgrammingPracticeTutorialsKaistCs109/index.html
ProgrammingPracticeTutorialsKaistCs109/css/__init__.py
ProgrammingPracticeTutorialsKaistCs109/css/annotations.css
ProgrammingPracticeTutorialsKaistCs109/css/main.css
ProgrammingPracticeTutorialsKaistCs109/css/normalize.css
ProgrammingPracticeTutorialsKaistCs109/css/popup.css
ProgrammingPracticeTutorialsKaistCs109/font/__init__.py
ProgrammingPracticeTutorialsKaistCs109/font/fontello.eot
ProgrammingPracticeTutorialsKaistCs109/font/fontello.svg
ProgrammingPracticeTutorialsKaistCs109/font/fontello.ttf
ProgrammingPracticeTutorialsKaistCs109/font/fontello.woff
ProgrammingPracticeTutorialsKaistCs109/img/__init__.py
ProgrammingPracticeTutorialsKaistCs109/img/annotator-glyph-sprite.png
ProgrammingPracticeTutorialsKaistCs109/img/annotator-icon-sprite.png
ProgrammingPracticeTutorialsKaistCs109/img/apple-touch-icon.png
ProgrammingPracticeTutorialsKaistCs109/img/cancelfullscreen.png
ProgrammingPracticeTutorialsKaistCs109/img/close.png
ProgrammingPracticeTutorialsKaistCs109/img/fullscreen.png
ProgrammingPracticeTutorialsKaistCs109/img/loader.gif
ProgrammingPracticeTutorialsKaistCs109/img/menu-icon.png
ProgrammingPracticeTutorialsKaistCs109/img/save.png
ProgrammingPracticeTutorialsKaistCs109/img/saved.png
ProgrammingPracticeTutorialsKaistCs109/img/settings-s.png
ProgrammingPracticeTutorialsKaistCs109/img/settings.png
ProgrammingPracticeTutorialsKaistCs109/img/star.png
ProgrammingPracticeTutorialsKaistCs109/js/__init__.py
ProgrammingPracticeTutorialsKaistCs109/js/epub.js
ProgrammingPracticeTutorialsKaistCs109/js/epub.min.js
ProgrammingPracticeTutorialsKaistCs109/js/epub.min.map
ProgrammingPracticeTutorialsKaistCs109/js/hooks.min.js
ProgrammingPracticeTutorialsKaistCs109/js/hooks.min.map
programming_practice_tutorials_kaist_cs109-2024.3.2.0.dist-info/METADATA
programming_practice_tutorials_kaist_cs109-2024.3.2.0.dist-info/WHEEL
programming_practice_tutorials_kaist_cs109-2024.3.2.0.dist-info/entry_points.txt
programming_practice_tutorials_kaist_cs109-2024.3.2.0.dist-info/top_level.txt
programming_practice_tutorials_kaist_cs109-2024.3.2.0.dist-info/RECORD
